README.rst
setup.cfg
setup.py
aiobinance/__init__.py
aiobinance/client.py
aiobinance/depthcache.py
aiobinance/enums.py
aiobinance/exceptions.py
aiobinance/helpers.py
aiobinance/websockets.py
python_binance_aio.egg-info/PKG-INFO
python_binance_aio.egg-info/SOURCES.txt
python_binance_aio.egg-info/dependency_links.txt
python_binance_aio.egg-info/requires.txt
python_binance_aio.egg-info/top_level.txt