Metadata-Version: 1.1
Name: python-binance-aio
Version: 0.0.4
Summary: Asynchronous Binance REST API python implementation
Home-page: https://github.com/BlockHub/python-binance-aio
Author: Karel Kubat
Author-email: Karel@blockhub.nl
License: MIT
Keywords: binance exchange rest api bitcoin ethereum btc eth neo aiohttp asyncio
Platform: UNKNOWN
Classifier: Intended Audience :: Developers
Classifier: License :: OSI Approved :: MIT License
Classifier: Operating System :: OS Independent
Classifier: Programming Language :: Python :: 3.6
Classifier: Programming Language :: Python
Classifier: Topic :: Software Development :: Libraries :: Python Modules
